dapple/__init__.py
dapple/auto.py
dapple/canvas.py
dapple/color.py
dapple/preprocess.py
dapple/adapters/__init__.py
dapple/adapters/ansi.py
dapple/adapters/cairo.py
dapple/adapters/matplotlib.py
dapple/adapters/numpy.py
dapple/adapters/pil.py
dapple/extras/__init__.py
dapple/extras/common.py
dapple/extras/csvcat/__init__.py
dapple/extras/csvcat/cli.py
dapple/extras/csvcat/csvcat.py
dapple/extras/datacat/__init__.py
dapple/extras/datacat/cli.py
dapple/extras/datacat/datacat.py
dapple/extras/funcat/__init__.py
dapple/extras/funcat/funcat.py
dapple/extras/imgcat/__init__.py
dapple/extras/imgcat/imgcat.py
dapple/extras/mdcat/__init__.py
dapple/extras/mdcat/mdcat.py
dapple/extras/pdfcat/__init__.py
dapple/extras/pdfcat/pdfcat.py
dapple/extras/vidcat/__init__.py
dapple/extras/vidcat/vidcat.py
dapple/extras/vizlib/__init__.py
dapple/extras/vizlib/charts.py
dapple/extras/vizlib/colors.py
dapple/extras/vizlib/render.py
dapple/renderers/__init__.py
dapple/renderers/ascii.py
dapple/renderers/braille.py
dapple/renderers/fingerprint.py
dapple/renderers/kitty.py
dapple/renderers/quadrants.py
dapple/renderers/sextants.py
dapple/renderers/sixel.py
dapple-0.5.1.dist-info/METADATA
dapple-0.5.1.dist-info/WHEEL
dapple-0.5.1.dist-info/entry_points.txt
dapple-0.5.1.dist-info/top_level.txt
dapple-0.5.1.dist-info/RECORD
