Metadata-Version: 2.4
Name: dapple
Version: 0.5.1
Summary: Unified terminal graphics library - render bitmaps to braille, blocks, ASCII, sixel, and kitty
Author: spinoza
License-Expression: MIT
Project-URL: Homepage, https://github.com/queelius/dapple
Project-URL: Repository, https://github.com/queelius/dapple
Project-URL: Documentation, https://queelius.github.io/dapple/
Classifier: Development Status :: 3 - Alpha
Classifier: Environment :: Console
Classifier: Intended Audience :: Developers
Classifier: Operating System :: OS Independent
Classifier: Programming Language :: Python :: 3
Classifier: Programming Language :: Python :: 3.10
Classifier: Programming Language :: Python :: 3.11
Classifier: Programming Language :: Python :: 3.12
Classifier: Topic :: Multimedia :: Graphics
Classifier: Topic :: Terminals
Requires-Python: >=3.10
Requires-Dist: numpy>=1.20
Provides-Extra: adapters
Requires-Dist: pillow>=9.0; extra == "adapters"
Requires-Dist: matplotlib>=3.5; extra == "adapters"
Provides-Extra: imgcat
Requires-Dist: pillow>=9.0; extra == "imgcat"
Provides-Extra: funcat
Provides-Extra: pdfcat
Requires-Dist: pillow>=9.0; extra == "pdfcat"
Requires-Dist: pypdfium2>=4.0; extra == "pdfcat"
Provides-Extra: mdcat
Requires-Dist: pillow>=9.0; extra == "mdcat"
Requires-Dist: rich>=13.0; extra == "mdcat"
Provides-Extra: vidcat
Requires-Dist: pillow>=9.0; extra == "vidcat"
Provides-Extra: vizlib
Provides-Extra: csvcat
Provides-Extra: datacat
Provides-Extra: all-tools
Requires-Dist: dapple[csvcat,datacat,funcat,imgcat,mdcat,pdfcat,vidcat]; extra == "all-tools"
Provides-Extra: dev
Requires-Dist: pytest>=7.0; extra == "dev"
Requires-Dist: pytest-cov>=4.0; extra == "dev"
Requires-Dist: dapple[adapters,all-tools]; extra == "dev"
Provides-Extra: docs
Requires-Dist: mkdocs-material>=9.0; extra == "docs"
Provides-Extra: all
Requires-Dist: dapple[adapters,all-tools,dev]; extra == "all"
